Metadata-Version: 1.1
Name: Flask-Material
Version: 0.0.9
Summary: An extension that includes Materialize CSS (http://materializecss.com/) in your project, without any boilerplate code.
Home-page: https://github.com/HellerCommaA/flask-materialize
Author: Adam Heller
Author-email: heller@mailbox.org
License: MIT
Platform: any
Classifier: Environment :: Web Environment
Classifier: Intended Audience :: Developers
Classifier: License :: OSI Approved :: MIT License
Classifier: Operating System :: OS Independent
Classifier: Programming Language :: Python
Classifier: Programming Language :: Python :: 2
Classifier: Topic :: Internet :: WWW/HTTP :: Dynamic Content
Classifier: Topic :: Software Development :: Libraries :: Python Modules
